arvideo.py
arvideo-0.0.1.dist-info/METADATA
arvideo-0.0.1.dist-info/WHEEL
arvideo-0.0.1.dist-info/top_level.txt
arvideo-0.0.1.dist-info/RECORD
