Metadata-Version: 2.1
Name: arvideo
Version: 0.0.1
Summary: Hologram a video in a real-world entity surrounded with ArUco markers.
Home-page: https://github.com/Akash-Peace
Author: Akash.A
Author-email: akashcse2000@gmail.com
License: MIT
Platform: UNKNOWN
Classifier: Development Status :: 5 - Production/Stable
Classifier: Intended Audience :: Developers
Classifier: Topic :: Software Development :: Build Tools
Classifier: License :: OSI Approved :: MIT License
Classifier: Programming Language :: Python :: 3
Classifier: Operating System :: OS Independent
Requires-Dist: opencv-contrib-python (==4.1.0.25)
Requires-Dist: numpy
